nsi25perlin/__init__.py
nsi25perlin/perlinNoise.py
nsi25Perlin-0.0.2.dist-info/LICENSE
nsi25Perlin-0.0.2.dist-info/METADATA
nsi25Perlin-0.0.2.dist-info/WHEEL
nsi25Perlin-0.0.2.dist-info/top_level.txt
nsi25Perlin-0.0.2.dist-info/RECORD
