Metadata-Version: 2.2
Name: nsi25Perlin
Version: 0.0.2
Summary: nsi25Perlin is a small module that implements Perlin's noise.
Author-email: Artic <artic.admisoffi@gmail.com>
Project-URL: Homepage, https://github.com/ArticOff/nsi25Perlin
Classifier: Programming Language :: Python :: 3
Classifier: License :: OSI Approved :: GNU General Public License v3 (GPLv3)
Classifier: Operating System :: OS Independent
Requires-Python: >=3.10
License-File: LICENSE
Requires-Dist: proto-obj>=0.0.4
